{
  "movies": [
    {
      "id": "1",
      "title": "Ozzy Osbourne: God Bless Ozzy Osbourne",
      "year": 2011,
      "genre": "Documentary, Music",
      "rating": 4
    },
    {
      "id": "2",
      "title": "Randy Rhoads: Reflections of a Guitar Icon",
      "year": 2022,
      "genre": "Documentary, Music",
      "rating": 5
    },
    {
      "id": "3",
      "title": "Rush: Beyond the Lighted Stage",
      "year": 2010,
      "genre": "Documentary, Music",
      "rating": 5
    }
  ]
}